{
  "equipment_type": "対空砲",
  "common": {
    "名前": "40 mm OQF Mark IV",
    "ID": "SMAA056",
    "重量": 518.0,
    "人員": 18,
    "開発年": 1941.0,
    "開発国": "ENG",
    "必要資源_鉄": 1,
    "必要資源_クロム": 0,
    "必要資源_アルミ": 0,
    "必要資源_タングステン": 0,
    "必要資源_ゴム": 0
  },
  "specific": {
    "shell_weight_g": 894.0,
    "initial_velocity_mps": 853.0,
    "rounds_per_minute": 85.0,
    "caliber_mm": 4.0,
    "barrel_length": 56.3,
    "barrel_count": 1,
    "max_elevation": "90",
    "turret_count": 1,
    "shell_weight_kg": 0,
    "caliber_cm": 0
  }
}