{
  "name": "偵察巡洋艦",
  "id": "SSH_CS_1",
  "weight": 3449.5,
  "length": 122.34,
  "width": 12.34,
  "power": 23116.5,
  "speed": 26.26,
  "range": 3539.0,
  "cruise_speed": 14.75,
  "fuel_capacity": 737.25,
  "armor_max": 42.0,
  "armor_min": 4.0,
  "hull_structure_id": 1.24,
  "armor_type_id": 1.2,
  "crew": 300.38,
  "country": "NULL",
  "class": "CS",
  "year": 1910.0,
  "archetype": "CL - 二等巡洋艦",
  "type": "CS - 偵察巡洋艦",
  "hull_structure": "ミディアム",
  "armor_type": "標準装甲",
  "slots": {
    "PA": " ",
    "SA": "-",
    "PSA": " ",
    "SSA": "-",
    "PLA": " ",
    "SLA": "="
  }
}