{
  "name": "Kirov級_II",
  "id": "USH_SOV_CA_Kirov_class_II",
  "weight": 9280.0,
  "length": 187.0,
  "width": 17.4,
  "power": 129700.0,
  "speed": 36.0,
  "range": 3750.0,
  "cruise_speed": 18.0,
  "fuel_capacity": 1280.0,
  "armor_max": 50.0,
  "armor_min": 50.0,
  "hull_structure_id": 2.0,
  "armor_type_id": 2.0,
  "crew": 734.0,
  "country": "SOV",
  "class": "CA_3",
  "year": 1938.0,
  "archetype": "CA - 一等巡洋艦",
  "type": "CA - 重巡・一等巡洋艦",
  "main_engine_id": "",
  "auxiliary_engine_ids": [],
  "engine_count": {
    "main": 1,
    "auxiliary": 0
  },
  "max_speed": "36.00",
  "naval_range": "3750.00",
  "hull_structure": "近代型",
  "armor_type": "複合装甲",
  "slots": {
    "PA": " ",
    "SA": " ",
    "PSA": " ",
    "SSA": " ",
    "PLA": " ",
    "SLA": " "
  }
}